LICENSE
MANIFEST.in
README.md
setup.py
powerpy/__init__.py
powerpy/currying.py
powerpy/synchronize.py
powerpy/type_checking.py
powerpy.egg-info/PKG-INFO
powerpy.egg-info/SOURCES.txt
powerpy.egg-info/dependency_links.txt
powerpy.egg-info/top_level.txt
powerpy/dynamic/__init__.py
powerpy/dynamic/memoization.py
powerpy/pattern/__init__.py
powerpy/pattern/behavioral/__init__.py
powerpy/pattern/behavioral/observable.py
powerpy/pattern/behavioral/pipeline.py
powerpy/pattern/behavioral/responsibility.py
powerpy/pattern/creational/__init__.py
powerpy/pattern/creational/singleton.py
powerpy/pattern/structural/__init__.py
powerpy/pattern/structural/flyweight.py
powerpy/raw/__init__.py
powerpy/raw/cstruct.py