Metadata-Version: 2.1
Name: powerpy
Version: 0.1.0
Summary: A collection of constructs for Python3
Home-page: https://github.com/jacopodl/powerpy
Author: Jacopo De Luca
Author-email: jacopo.delu@gmail.com
License: MIT
Keywords: awesome,library,patterns,constructs
Platform: UNKNOWN
Classifier: Development Status :: 4 - Beta
Classifier: Intended Audience :: Developers
Classifier: License :: OSI Approved :: MIT License
Classifier: Programming Language :: Python :: 3
